{
  "Australia": [
    {
      "name": "Australian Capital Territory",
      "url": "https://www.anytimemailbox.com/s/manuka-2-captain-cook-crescent"
    },
    {
      "region": "New South Wales",
      "urls": [
        {
          "name": "Blacktown",
          "url": "https://www.anytimemailbox.com/s/blacktown-10-12-flushcombe-road"
        },
        {
          "name": "Bondi Junction",
          "url": "https://www.anytimemailbox.com/s/bondi-junction-30-denison-street"
        },
        {
          "name": "Hurstville",
          "url": "https://www.anytimemailbox.com/s/hurstville-1-barratt-street"
        },
        {
          "name": "Lane Cove",
          "url": "https://www.anytimemailbox.com/s/lane-cove-79-83-longueville-road"
        },
        {
          "name": "Macquarie Park",
          "url": "https://www.anytimemailbox.com/s/macquarie-park-talavera-road"
        },
        {
          "name": "Neutral Bay",
          "url": "https://www.anytimemailbox.com/s/neutral-bay-4-young-street"
        },
        {
          "name": "North Sydney",
          "url": "https://www.anytimemailbox.com/s/north-sydney-6-50-miller-street"
        },
        {
          "name": "Parramatta",
          "url": "https://www.anytimemailbox.com/s/parramatta-29-smith-street"
        },
        {
          "name": "Sydney - Bathurst St",
          "url": "https://www.anytimemailbox.com/s/sydney-97-99-bathurst-street"
        },
        {
          "name": "Ultimo",
          "url": "https://www.anytimemailbox.com/s/ultimo-144-mountain-street"
        }
      ]
    },
    {
      "region": "Queensland",
      "urls": [
        {
          "name": "Archerfield",
          "url": "https://www.anytimemailbox.com/s/archerfield-30d-121-kerry-road"
        },
        {
          "name": "Brisbane - Adelaide St",
          "url": "https://www.anytimemailbox.com/s/brisbane-241-adelaide-street"
        },
        {
          "name": "Broadbeach",
          "url": "https://www.anytimemailbox.com/s/broadbeach-110-albert-avenue"
        },
        {
          "name": "Capalaba",
          "url": "https://www.anytimemailbox.com/s/capalaba-66-old-cleveland-road"
        },
        {
          "name": "Currumbin Waters",
          "url": "https://www.anytimemailbox.com/s/currumbin-waters-52-currumbin-creek-road"
        },
        {
          "name": "Eight Mile Plains",
          "url": "https://www.anytimemailbox.com/s/eight-mile-plains-7-clunies-ross-court"
        },
        {
          "name": "Hope Island",
          "url": "https://www.anytimemailbox.com/s/hope-island-9340-hope-island-road"
        },
        {
          "name": "Loganholme",
          "url": "https://www.anytimemailbox.com/s/loganholme-416-18-beenleigh-redland-bay-road"
        },
        {
          "name": "Milton",
          "url": "https://www.anytimemailbox.com/s/milton-47-park-road"
        },
        {
          "name": "Robina",
          "url": "https://www.anytimemailbox.com/s/robina-514-christine-avenue"
        },
        {
          "name": "West End",
          "url": "https://www.anytimemailbox.com/s/west-end-156-boundary-street"
        }
      ]
    },
    {
      "region": "Victoria",
      "urls": [
        {
          "name": "Camberwell",
          "url": "https://www.anytimemailbox.com/s/camberwell-738-burke-road"
        },
        {
          "name": "Elsternwick",
          "url": "https://www.anytimemailbox.com/s/elsternwick-283-glen-huntly-road"
        },
        {
          "name": "Glen Waverley",
          "url": "https://www.anytimemailbox.com/s/glen-waverley-17-coleman-parade"
        },
        {
          "name": "Kew",
          "url": "https://www.anytimemailbox.com/s/kew-16-cotham-road"
        },
        {
          "name": "Malvern",
          "url": "https://www.anytimemailbox.com/s/malvern-45-glenferrie-road"
        },
        {
          "name": "Melbourne - Little Bourke St",
          "url": "https://www.anytimemailbox.com/s/melbourne-439-little-bourke-street"
        },
        {
          "name": "Point Cook",
          "url": "https://www.anytimemailbox.com/s/point-cook-22-30-wallace-avenue"
        }
      ]
    },
    {
      "region": "Western Australia",
      "urls": [
        {
          "name": "Applecross",
          "url": "https://www.anytimemailbox.com/s/applecross-level-1896-canning-hwy"
        },
        {
          "name": "Canning Vale - Bannister Rd",
          "url": "https://www.anytimemailbox.com/s/canning-vale-15166466-bannister-road"
        },
        {
          "name": "Perth - St Georges Ter (50)",
          "url": "https://www.anytimemailbox.com/s/perth-50-st-georges-terrace"
        },
        {
          "name": "West Perth",
          "url": "https://www.anytimemailbox.com/s/west-perth-1101-hay-street"
        }
      ]
    }
  ],
  "Brazil": [
    {
      "region": "Rio de Janeiro",
      "urls": [
        {
          "name": "Niteroi",
          "url": "https://www.anytimemailbox.com/s/niteroi-r-ator-paulo-gustavo-265-lj-207-icarai"
        },
        {
          "name": "Rio de Janeiro - Av Rio Branco",
          "url": "https://www.anytimemailbox.com/s/rio-de-janeiro-av-rio-branco-133-lj-f-centro"
        },
        {
          "name": "Rio de Janeiro - Rua Figueiredo de Magalhaes",
          "url": "https://www.anytimemailbox.com/s/rio-de-janeiro-rua-figueiredo-de-magalhaes-219-sl-"
        },
        {
          "name": "Rio de Janeiro - Rua Gen Urquiza",
          "url": "https://www.anytimemailbox.com/s/rio-de-janeiro-r-gen-urquiza-67-lj-b-leblon"
        }
      ]
    }
  ],
  "Bulgaria": [
    {
      "name": "Lovech",
      "url": "https://www.anytimemailbox.com/s/troyan-14-vasil-levski-street"
    },
    {
      "name": "Plovdiv",
      "url": "https://www.anytimemailbox.com/s/bulgaria-plovdiv"
    },
    {
      "region": "Sofia-Grad",
      "urls": [
        {
          "name": "Sofia - Donka Ushlinova St",
          "url": "https://www.anytimemailbox.com/s/sofia-1766-sofia-2-donka-ushlinova-street"
        },
        {
          "name": "Sofia - Vitosha Blvd",
          "url": "https://www.anytimemailbox.com/s/sofia-99-vitosha-blvd"
        }
      ]
    }
  ],
  "Canada": [
    {
      "name": "Manitoba",
      "url": "https://www.anytimemailbox.com/s/winnipeg-700-dovercourt-drive"
    },
    {
      "region": "Alberta",
      "urls": [
        {
          "name": "Calgary - 3 St",
          "url": "https://www.anytimemailbox.com/s/calgary-1122-3-street-se"
        },
        {
          "name": "Calgary - Dalhousie Dr",
          "url": "https://www.anytimemailbox.com/s/calgary-5005-dalhousie-drive-nw"
        },
        {
          "name": "Calgary - Farrell Rd",
          "url": "https://www.anytimemailbox.com/s/calgary-7070e-farrell-rd-se"
        },
        {
          "name": "Calgary - Macleod Trail",
          "url": "https://www.anytimemailbox.com/s/calgary-5211-macleod-trail-sw"
        },
        {
          "name": "Calgary - Stewart Green",
          "url": "https://www.anytimemailbox.com/s/calgary-246-stewart-green-sw"
        },
        {
          "name": "Canmore",
          "url": "https://www.anytimemailbox.com/s/canmore-1080-railway-avenue"
        },
        {
          "name": "Cochrane - Railway St",
          "url": "https://www.anytimemailbox.com/s/cochrane-225-railway-street-east"
        },
        {
          "name": "Grande Prairie",
          "url": "https://www.anytimemailbox.com/s/grande-prairie-10008-103-ave"
        },
        {
          "name": "Leduc",
          "url": "https://www.anytimemailbox.com/s/leduc-4810-50th-ave"
        },
        {
          "name": "St Albert",
          "url": "https://www.anytimemailbox.com/s/st-albert-12-hebert-road"
        }
      ]
    },
    {
      "region": "British Columbia",
      "urls": [
        {
          "name": "Chilliwack - Yale Rd",
          "url": "https://www.anytimemailbox.com/s/chilliwack-44322-yale-road"
        },
        {
          "name": "Enderby",
          "url": "https://www.anytimemailbox.com/s/enderby-702-russell-avenue"
        },
        {
          "name": "Kelowna",
          "url": "https://www.anytimemailbox.com/s/kelowna-7-2070-harvey-ave"
        },
        {
          "name": "Vancouver",
          "url": "https://www.anytimemailbox.com/s/vancouver-5307-victoria-drive"
        },
        {
          "name": "Vancouver - Howe St",
          "url": "https://www.anytimemailbox.com/s/vancouver-329-howe-street"
        },
        {
          "name": "Vancouver - Victoria Dr",
          "url": "https://www.anytimemailbox.com/s/vancouver-5780-victoria-drive"
        }
      ]
    },
    {
      "region": "Ontario",
      "urls": [
        {
          "name": "Acton",
          "url": "https://www.anytimemailbox.com/s/acton-a-56-mill-street-east"
        },
        {
          "name": "Ajax",
          "url": "https://www.anytimemailbox.com/s/ajax-75-bayly-street-west"
        },
        {
          "name": "Brampton - Bramalea Rd",
          "url": "https://www.anytimemailbox.com/s/brampton-45-bramalea-road"
        },
        {
          "name": "Brampton - Clark Blvd",
          "url": "https://www.anytimemailbox.com/s/brampton-1900-clark-blvd"
        },
        {
          "name": "Brampton - Hurontario St",
          "url": "https://www.anytimemailbox.com/s/brampton-7700-hurontario-street"
        },
        {
          "name": "Cambridge",
          "url": "https://www.anytimemailbox.com/s/cambridge-107-1025-king-st-e"
        },
        {
          "name": "Cornwall",
          "url": "https://www.anytimemailbox.com/s/cornwall-327-2nd-street-east"
        },
        {
          "name": "Etobicoke - Dundas St (4243c)",
          "url": "https://www.anytimemailbox.com/s/etobicoke-4243c-dundas-street-west"
        },
        {
          "name": "Etobicoke - Dundas St (5343)",
          "url": "https://www.anytimemailbox.com/s/etobicoke-5343-dundas-street-west"
        },
        {
          "name": "Georgetown - Guelph St",
          "url": "https://www.anytimemailbox.com/s/georgetown-354-guelph-street"
        },
        {
          "name": "Hamilton - King St",
          "url": "https://www.anytimemailbox.com/s/hamilton-7-2-king-street-west"
        },
        {
          "name": "Mississauga - Burnhamthorpe Rd",
          "url": "https://www.anytimemailbox.com/s/mississauga-50-burnhamthorpe-road-west"
        },
        {
          "name": "Mississauga - Lenworth Dr",
          "url": "https://www.anytimemailbox.com/s/mississauga-3166-lenworth-drive"
        },
        {
          "name": "Mississauga - Tomken Rd",
          "url": "https://www.anytimemailbox.com/s/mississauga-6705-tomken-road"
        },
        {
          "name": "North York - Weston Rd",
          "url": "https://www.anytimemailbox.com/s/north-york-2544-weston-road"
        },
        {
          "name": "Oshawa",
          "url": "https://www.anytimemailbox.com/s/oshawa-50-richmond-street-e"
        },
        {
          "name": "Ottawa",
          "url": "https://www.anytimemailbox.com/s/ottawa-5-2164-montreal-road"
        },
        {
          "name": "Richmond Hill",
          "url": "https://www.anytimemailbox.com/s/richmond-hill-10225-yonge-street"
        },
        {
          "name": "Thornhill",
          "url": "https://www.anytimemailbox.com/s/thornhill-6d-7398-yonge-street"
        },
        {
          "name": "Toronto - Davenport Rd",
          "url": "https://www.anytimemailbox.com/s/toronto-1463-davenport-road"
        },
        {
          "name": "Toronto - Dundas St",
          "url": "https://www.anytimemailbox.com/s/toronto-2967-dundas-st-w"
        },
        {
          "name": "Toronto - Rimrock Rd",
          "url": "https://www.anytimemailbox.com/s/toronto-265-rimrock-road"
        },
        {
          "name": "Toronto - Yonge St",
          "url": "https://www.anytimemailbox.com/s/toronto-2482-yonge-street"
        },
        {
          "name": "Vaughan",
          "url": "https://www.anytimemailbox.com/s/vaughan-2160-hwy-7"
        },
        {
          "name": "Windsor",
          "url": "https://www.anytimemailbox.com/s/windsor-2375-tecumseh-road-west"
        },
        {
          "name": "Woodbridge",
          "url": "https://www.anytimemailbox.com/s/woodbridge-14-3650-langstaff-road"
        }
      ]
    },
    {
      "region": "Québec",
      "urls": [
        {
          "name": "Brossard - Boulevard Leduc",
          "url": "https://www.anytimemailbox.com/s/brossard-9000-boulevard-leduc"
        },
        {
          "name": "Brossard - Grande Allee",
          "url": "https://www.anytimemailbox.com/s/brossard-5645-grande-allee-local-130"
        },
        {
          "name": "Brossard - Taschereau Blvd",
          "url": "https://www.anytimemailbox.com/s/brossard-6185-taschereau-blvd"
        },
        {
          "name": "Longueuil",
          "url": "https://www.anytimemailbox.com/s/longueuil-1682-ch-du-tremblay"
        },
        {
          "name": "Montréal - Bd de L'Acadie",
          "url": "https://www.anytimemailbox.com/s/montreal-9150-bd-de-lacadie"
        },
        {
          "name": "Montréal - Henri-Bourassa Blvd",
          "url": "https://www.anytimemailbox.com/s/montreal-1405-henri-bourassa-blvd-w"
        },
        {
          "name": "Montréal - Notre-Dame St",
          "url": "https://www.anytimemailbox.com/s/montreal-1235-notre-dame-street-west"
        },
        {
          "name": "Montréal - Queen Mary Rd",
          "url": "https://www.anytimemailbox.com/s/montreal-5172-queen-mary-road"
        },
        {
          "name": "Montréal - Rue Jean-Talon O",
          "url": "https://www.anytimemailbox.com/s/montr%C3%A9al-5400-rue-jean-talon-o"
        },
        {
          "name": "Montréal - Rue Lucien-L'Allier",
          "url": "https://www.anytimemailbox.com/s/montreal-1055-rue-lucien-lallier"
        },
        {
          "name": "Montréal - Rue Mackay",
          "url": "https://www.anytimemailbox.com/s/montreal-1438-rue-mackay-street"
        },
        {
          "name": "Montréal - Rue Saint-Denis",
          "url": "https://www.anytimemailbox.com/s/montreal-4388-rue-saint-denis"
        },
        {
          "name": "Montréal - Rue Sainte-Catherine",
          "url": "https://www.anytimemailbox.com/s/montreal-365-rue-sainte-catherine-est"
        },
        {
          "name": "Montréal - Saint Denis St",
          "url": "https://www.anytimemailbox.com/s/montreal-3450-saint-denis-street"
        },
        {
          "name": "Montréal - Shevchenko Blvd",
          "url": "https://www.anytimemailbox.com/s/montreal-1500-shevchenko-blvd"
        },
        {
          "name": "Quebec City",
          "url": "https://www.anytimemailbox.com/s/quebec-city-1398-ch-ste-foy"
        },
        {
          "name": "Saint-Constant",
          "url": "https://www.anytimemailbox.com/s/saint-constant-87-rue-st-pierre"
        }
      ]
    }
  ],
  "Caribbean": [
    {
      "region": "Cayman Islands",
      "urls": [
        {
          "name": "Camana Bay",
          "url": "https://www.anytimemailbox.com/s/camana-bay-10-market-street"
        },
        {
          "name": "Grand Cayman",
          "url": "https://www.anytimemailbox.com/s/grand-cayman-52a-edgewater-way"
        }
      ]
    },
    {
      "region": "Virgin Islands (US)",
      "urls": [
        {
          "name": "St Thomas",
          "url": "https://www.anytimemailbox.com/s/charlotte-amalie-9602-estate-thomas"
        }
      ]
    }
  ],
  "China": [
    {
      "name": "Guangdong",
      "url": "https://www.anytimemailbox.com/s/shenzhen-xinyuan-garden-meigang-road"
    },
    {
      "name": "Shandong",
      "url": "https://www.anytimemailbox.com/s/qingdao-wu-zhou-lu-602"
    },
    {
      "name": "Zhejiang",
      "url": "https://www.anytimemailbox.com/s/hangzhou-no82-fuyan-road-xianlin-yuhang-district"
    },
    {
      "region": "Shaanxi",
      "urls": [
        {
          "name": "Hanzhong",
          "url": "https://www.anytimemailbox.com/s/hanzhong-no-22-middle-section-of-xinjie-foping-cou"
        },
        {
          "name": "Xi'an",
          "url": "https://www.anytimemailbox.com/s/xian-changanqu-wanke-mianhua-15-1912"
        }
      ]
    }
  ],
  "Croatia": [
    {
      "name": "Central Croatia",
      "url": "https://www.anytimemailbox.com/s/krizevci-ul-bana-josipa-jelacica-1"
    },
    {
      "region": "Zagreb",
      "urls": [
        {
          "name": "Središće - Ul Brune Bušića",
          "url": "https://www.anytimemailbox.com/s/sredi%C5%A1%C4%87e-ul-brune-bu%C5%A1i%C4%87a-42"
        },
        {
          "name": "Zagreb - Remetinecka Cesta",
          "url": "https://www.anytimemailbox.com/s/zagreb-remetinecka-cesta-kajzerica"
        },
        {
          "name": "Zagreb - Vlaska Ul",
          "url": "https://www.anytimemailbox.com/s/zagreb-vlaska-ulica-45"
        }
      ]
    }
  ],
  "Czech Republic": [
    {
      "region": "Prague",
      "urls": [
        {
          "name": "Prague",
          "url": "https://www.anytimemailbox.com/s/prague-na-piskach-126665"
        },
        {
          "name": "Praha 7-Holešovice - Jankovcova 51638",
          "url": "https://www.anytimemailbox.com/s/praha-7-hole%C5%A1ovice-jankovcova-51638"
        }
      ]
    }
  ],
  "France": [
    {
      "name": "Hauts-de-France",
      "url": "https://www.anytimemailbox.com/s/nogent-sur-oise-2-rue-alexandre-ribot"
    },
    {
      "region": "Île-de-France",
      "urls": [
        {
          "name": "Paris",
          "url": "https://www.anytimemailbox.com/s/paris-13-rue-la-bo%C3%A9tie"
        }
      ]
    }
  ],
  "Greece": [
    {
      "name": "Greater Athens",
      "url": "https://www.anytimemailbox.com/s/athens-ipirou-4a"
    },
    {
      "name": "Karpathos",
      "url": "https://www.anytimemailbox.com/s/karpathos-28-oktovriou"
    }
  ],
  "Hong Kong": [
    {
      "name": "Kowloon",
      "url": "https://www.anytimemailbox.com/s/kwun-tong-11-shing-yip-street"
    },
    {
      "region": "Hong Kong Island",
      "urls": [
        {
          "name": "Sheung Wan",
          "url": "https://www.anytimemailbox.com/s/sheung-wan-54-jervois-street"
        }
      ]
    }
  ],
  "Indonesia": [
    {
      "name": "Balikpapan",
      "url": "https://www.anytimemailbox.com/s/indonesia-balikpapan"
    },
    {
      "name": "Daerah Istimewa",
      "url": "https://www.anytimemailbox.com/s/yogyakarta-jalan-gamping-tengah-13-gamping-lor-amb"
    },
    {
      "name": "Jakarta",
      "url": "https://www.anytimemailbox.com/s/central-jakarta-jl-mh-thamrin-no20"
    }
  ],
  "Ireland": [
    {
      "region": "Dublin",
      "urls": [
        {
          "name": "Dublin",
          "url": "https://www.anytimemailbox.com/s/dublin-g5-3015-lake-drive"
        },
        {
          "name": "Dublin - Sir John Rogersons Quay",
          "url": "https://www.anytimemailbox.com/s/dublin-77-sir-john-rogersons-quay"
        },
        {
          "name": "Dun Laoghaire",
          "url": "https://www.anytimemailbox.com/s/dun-laoghaire-s23-the-pottery-road"
        }
      ]
    }
  ],
  "Malaysia": [
    {
      "name": "Penang",
      "url": "https://www.anytimemailbox.com/s/george-town-no-18a-unit-1-ground-fl-space-zgurneyw"
    },
    {
      "name": "Selangor",
      "url": "https://www.anytimemailbox.com/s/petaling-jaya-armanee"
    }
  ],
  "Mexico": [
    {
      "name": "Baja California",
      "url": "https://www.anytimemailbox.com/s/tijuana-mision-de-san-javier-10643-zona-urbana-rio"
    },
    {
      "name": "Guanajuato",
      "url": "https://www.anytimemailbox.com/s/leon-de-los-aldama-manuel-j-clouthier-304-jardines"
    },
    {
      "name": "Puebla",
      "url": "https://www.anytimemailbox.com/s/san-andres-cholula-atlixcayotl-1499-col-reserva-te"
    },
    {
      "name": "Quintana Roo",
      "url": "https://www.anytimemailbox.com/s/cancun-av-bonampak-sm-6-mz-1-lot-1"
    },
    {
      "name": "Sinaloa",
      "url": "https://www.anytimemailbox.com/s/culiacan-rosales-blvd-pedro-infante-2550-col-los-a"
    },
    {
      "name": "Tabasco",
      "url": "https://www.anytimemailbox.com/s/villahermosa-blvd-adolfo-ruiz-cortines-1344-atasta"
    },
    {
      "region": "Distrito Federal",
      "urls": [
        {
          "name": "Alvaro Obregon - Av Insurgentes",
          "url": "https://www.anytimemailbox.com/s/alvaro-obregon-av-insurgentes-sur-2453-tizapan-san"
        },
        {
          "name": "Alvaro Obregon - Prol P de la Reforma",
          "url": "https://www.anytimemailbox.com/s/alvaro-obregon-prol-p-de-la-reforma-1015-santa-fe-"
        },
        {
          "name": "Benito Juarez - Av Insurgentes (1602)",
          "url": "https://www.anytimemailbox.com/s/benito-juarez-av-insurgentes-sur-1602-credito-cons"
        },
        {
          "name": "Benito Juarez - Av Insurgentes (859)",
          "url": "https://www.anytimemailbox.com/s/benito-juarez-av-insurgentes-sur-859-napoles"
        },
        {
          "name": "Cuajimalpa de Morelos - Carr Mexico-Toluca",
          "url": "https://www.anytimemailbox.com/s/cuajimalpa-de-morelos-carr-mexico-toluca-5420-la-r"
        },
        {
          "name": "Cuajimalpa de Morelos - Mario Pani",
          "url": "https://www.anytimemailbox.com/s/cuajimalpa-de-morelos-mario-pani-400-col-lomas-de-"
        },
        {
          "name": "Cuauhtemoc - Av P de la Reforma (222-1)",
          "url": "https://www.anytimemailbox.com/s/cuauhtemoc-av-p-de-la-reforma-222-1-juarez"
        },
        {
          "name": "Cuauhtemoc - Av P de la Reforma (222-18)",
          "url": "https://www.anytimemailbox.com/s/cuauhtemoc-av-p-de-la-reforma-222-18-juarez"
        },
        {
          "name": "Cuauhtemoc - Av P de la Reforma (243)",
          "url": "https://www.anytimemailbox.com/s/cuauhtemoc-av-p-de-la-reforma-243-col-renacimiento"
        },
        {
          "name": "Cuauhtemoc - Av P de la Reforma (250-8)",
          "url": "https://www.anytimemailbox.com/s/cuauhtemoc-av-p-de-la-reforma-250-8-juarez"
        },
        {
          "name": "Cuauhtemoc - Av P de la Reforma (250-9)",
          "url": "https://www.anytimemailbox.com/s/cuauhtemoc-av-p-de-la-reforma-250-9-juarez"
        },
        {
          "name": "Cuauhtemoc - Av P de la Reforma (296)",
          "url": "https://www.anytimemailbox.com/s/cuauhtemoc-av-p-de-la-reforma-296-juarez"
        },
        {
          "name": "Cuauhtemoc - Av P de la Reforma (483)",
          "url": "https://www.anytimemailbox.com/s/cuauhtemoc-av-p-de-la-reforma-483"
        },
        {
          "name": "Cuauhtemoc - Av P de la Reforma (509)",
          "url": "https://www.anytimemailbox.com/s/cuauhtemoc-av-p-de-la-reforma-509"
        },
        {
          "name": "Cuauhtemoc - Gral Benjamin Hill",
          "url": "https://www.anytimemailbox.com/s/cuauhtemoc-gral-benjamin-hill-1-hipodromo-condesa"
        },
        {
          "name": "Miguel Hidalgo - Av Ejercito Nacional Mexicano",
          "url": "https://www.anytimemailbox.com/s/miguel-hidalgo-av-ejercito-nacional-mexicano-769-a"
        },
        {
          "name": "Miguel Hidalgo - Blvd Miguel de Cervantes Saavedra",
          "url": "https://www.anytimemailbox.com/s/miguel-hidalgo-blvd-miguel-de-cervantes-saavedra-2"
        },
        {
          "name": "Miguel Hidalgo - C Lago Zurich",
          "url": "https://www.anytimemailbox.com/s/miguel-hidalgo-c-lago-zurich-245-col-amp-granada"
        },
        {
          "name": "Naucalpan de Juarez - Blvd Manuel Avila Camacho",
          "url": "https://www.anytimemailbox.com/s/naucalpan-de-juarez-blvd-manuel-avila-camacho-5-co"
        },
        {
          "name": "Naucalpan de Juarez - Paseo Interlomas",
          "url": "https://www.anytimemailbox.com/s/naucalpan-de-juarez-paseo-interlomas-vialidad-de-l"
        }
      ]
    },
    {
      "region": "Jalisco",
      "urls": [
        {
          "name": "Guadalajara",
          "url": "https://www.anytimemailbox.com/s/guadalajara-av-de-las-americas-1500-col-country-cl"
        },
        {
          "name": "Puerto Vallarta",
          "url": "https://www.anytimemailbox.com/s/puerto-vallarta-lib-luis-donaldo-colosio-1834c-laz"
        },
        {
          "name": "Zapopan - Av Patria",
          "url": "https://www.anytimemailbox.com/s/zapopan-av-patria-2085-puerta-de-hierro"
        },
        {
          "name": "Zapopan - Blvd Puerta de Hierro",
          "url": "https://www.anytimemailbox.com/s/zapopan-blvd-puerta-de-hierro-5153-col-puerta-de-h"
        }
      ]
    },
    {
      "region": "Nuevo León",
      "urls": [
        {
          "name": "San Pedro Garza García - Av Batallon de San Patricio",
          "url": "https://www.anytimemailbox.com/s/san-pedro-garza-garc%C3%ADa-av-batallon-de-san-patricio"
        },
        {
          "name": "San Pedro Garza García - Av del Roble",
          "url": "https://www.anytimemailbox.com/s/san-pedro-garza-garc%C3%ADa-av-del-roble-660-valle-del-"
        },
        {
          "name": "San Pedro Garza García - Av Eugenio Garza Laguera",
          "url": "https://www.anytimemailbox.com/s/san-pedro-garza-garc%C3%ADa-av-eugenio-garza-laguera-es"
        },
        {
          "name": "San Pedro Garza García - Av Ricardo Margain Zozaya",
          "url": "https://www.anytimemailbox.com/s/san-pedro-garza-garc%C3%ADa-av-ricardo-margain-zozaya-5"
        }
      ]
    },
    {
      "region": "Querétaro",
      "urls": [
        {
          "name": "Santiago de Queretaro",
          "url": "https://www.anytimemailbox.com/s/santiago-de-queretaro-prol-bernardo-quintana-sur-3"
        }
      ]
    },
    {
      "region": "Yucatán",
      "urls": [
        {
          "name": "Merida",
          "url": "https://www.anytimemailbox.com/s/merida-prol-paseo-montejo-331-benito-juarez-nte"
        }
      ]
    }
  ],
  "Nigeria": [
    {
      "name": "Lagos",
      "url": "https://www.anytimemailbox.com/s/surulere-5-alhaji-tokan-street-alaka-estate"
    },
    {
      "name": "Rivers",
      "url": "https://www.anytimemailbox.com/s/port-harcourt-13-chief-gu-ake-road"
    }
  ],
  "Philippines": [
    {
      "name": "Bacolod",
      "url": "https://www.anytimemailbox.com/s/bacolod-2nd-flr-st-annes-bldg-lacson-st"
    },
    {
      "name": "Luzon",
      "url": "https://www.anytimemailbox.com/s/taguig-11th-flr-one-park-dr-bgc-9th-ave"
    }
  ],
  "Portugal": [
    {
      "region": "Algarve",
      "urls": [
        {
          "name": "Loule",
          "url": "https://www.anytimemailbox.com/s/loule-rua-homens-do-andor-n2a"
        },
        {
          "name": "Quarteira",
          "url": "https://www.anytimemailbox.com/s/quarteira-av-francisco-sa-carneiro-edif-golfinho"
        }
      ]
    }
  ],
  "Romania": [
    {
      "name": "Bucharest",
      "url": "https://www.anytimemailbox.com/s/pite%C8%99ti-strada-%C8%9Bepe%C8%99-vod%C4%83-7"
    },
    {
      "name": "North West",
      "url": "https://www.anytimemailbox.com/s/cluj-napoca-str-sarmisegetuza-17-19"
    }
  ],
  "Singapore": [
    {
      "region": "Central Region",
      "urls": [
        {
          "name": "Singapore - Cecil St",
          "url": "https://www.anytimemailbox.com/s/singapore-18-00-105-cecil-street"
        },
        {
          "name": "Singapore - Coleman St",
          "url": "https://www.anytimemailbox.com/s/singapore-3-coleman-street"
        }
      ]
    }
  ],
  "South Africa": [
    {
      "name": "Gauteng",
      "url": "https://www.anytimemailbox.com/s/johannesburg-atrium-on-5th-street-sandton"
    },
    {
      "name": "Western Cape",
      "url": "https://www.anytimemailbox.com/s/cape-town-1-bridgeway-road"
    }
  ],
  "Spain": [
    {
      "name": "Tarragona",
      "url": "https://www.anytimemailbox.com/s/lhospitalet-de-linfant-poligono-industrial-les-tap"
    },
    {
      "region": "Valencia",
      "urls": [
        {
          "name": "Castelló de la Plana",
          "url": "https://www.anytimemailbox.com/s/castello-de-la-plana-carrer-de-campoamor-27"
        },
        {
          "name": "Valencia",
          "url": "https://www.anytimemailbox.com/s/valencia-calle-pintor-zarinena-5-3"
        }
      ]
    }
  ],
  "Switzerland": [
    {
      "name": "Geneva",
      "url": "https://www.anytimemailbox.com/s/geneva-12-cp-525"
    },
    {
      "name": "Vaud",
      "url": "https://www.anytimemailbox.com/s/nyon-route-de-saint-cergue-24b"
    },
    {
      "name": "Zug",
      "url": "https://www.anytimemailbox.com/s/baar-blegistrasse-15"
    },
    {
      "name": "Zurich",
      "url": "https://www.anytimemailbox.com/s/zurich-hermetschloostrasse-77"
    }
  ],
  "Ukraine": [
    {
      "name": "Kyiv Oblast",
      "url": "https://www.anytimemailbox.com/s/kyiv-vul-borisa-hmyri-9v-187"
    },
    {
      "name": "Western Ukraine",
      "url": "https://www.anytimemailbox.com/s/lviv-stryjska-str-945"
    }
  ],
  "United Kingdom": [
    {
      "name": "East Midlands",
      "url": "https://www.anytimemailbox.com/s/nottingham-37-westminster-buildings"
    },
    {
      "region": "East Of England",
      "urls": [
        {
          "name": "Peterborough - Blenheim Ct",
          "url": "https://www.anytimemailbox.com/s/peterborough-4-blenheim-court"
        },
        {
          "name": "Peterborough - Wharf Rd",
          "url": "https://www.anytimemailbox.com/s/peterborough-unit-9a-wharf-road-industrial-estate-"
        }
      ]
    },
    {
      "region": "Greater London",
      "urls": [
        {
          "name": "Ilford - Clements Rd",
          "url": "https://www.anytimemailbox.com/s/london-25-29-clements-road"
        },
        {
          "name": "Ilford - Forest House",
          "url": "https://www.anytimemailbox.com/s/ilford-forest-house-3rd-floor"
        },
        {
          "name": "London - High St",
          "url": "https://www.anytimemailbox.com/s/london-1st-fl-415-high-st"
        },
        {
          "name": "London - Lansdowne Rd",
          "url": "https://www.anytimemailbox.com/s/london-2-lansdowne-road-croydon"
        },
        {
          "name": "London - Ludgate Hill",
          "url": "https://www.anytimemailbox.com/s/london-39-ludgate-hill"
        },
        {
          "name": "London - New North Rd",
          "url": "https://www.anytimemailbox.com/s/london-275-new-north-road"
        },
        {
          "name": "London - Regent St",
          "url": "https://www.anytimemailbox.com/s/london-207-regent-street"
        }
      ]
    }
  ]
}