{
  "country": "Croatia",
  "regions": [
    {
      "region": "Zagreb",
      "locations": [
        {
          "title": "Središće - Ul Brune Bušića",
          "price": {
            "amount": 10.0,
            "currency": "USD"
          },
          "address": "{Mail Boxes Etc.}, Središće, Zagreb 10020 Croatia",
          "latitude": "45.7819614",
          "longitude": "15.9869349",
          "plan_url": "https://www.anytimemailbox.com/s/sredi%C5%A1%C4%87e-ul-brune-bu%C5%A1i%C4%87a-42",
          "is_premier": false,
          "plans": [
            {
              "title": "Bronze",
              "monthly_price": {
                "amount": 10.0,
                "currency": "USD"
              },
              "monthly_button_url": "location.href='https://signup.anytimemailbox.com/signup/new?term=30&srvPlnId=27166&siftsessionid=175205937564949760afeprg8njbv&firstpagehit=https://www.anytimemailbox.com/s/blacktown-10-12-flushcombe-road'",
              "yearly_price": {
                "amount": 110.0,
                "currency": "USD"
              },
              "yearly_button_url": "location.href='https://signup.anytimemailbox.com/signup/new?term=360&srvPlnId=27166&siftsessionid=175205937564949760afeprg8njbv&firstpagehit=https://www.anytimemailbox.com/s/blacktown-10-12-flushcombe-road'",
              "features": {
                "Incoming Mail": "30 / month",
                "Open & Scan": "5 pages / month",
                "Forwarding": "Unlimited",
                "Recipients": "2"
              },
              "service_plan_id": "27166",
              "detailed_features": {
                "pricing": {
                  "monthly_price": {
                    "amount": 10.0,
                    "currency": "USD"
                  },
                  "monthly_button_url": "location.href='https://signup.anytimemailbox.com/signup/new?term=30&srvPlnId=27166&siftsessionid=175205937564949760afeprg8njbv&firstpagehit=https://www.anytimemailbox.com/s/blacktown-10-12-flushcombe-road'",
                  "yearly_price": {
                    "amount": 110.0,
                    "currency": "USD"
                  },
                  "yearly_button_url": "location.href='https://signup.anytimemailbox.com/signup/new?term=360&srvPlnId=27166&siftsessionid=175205937564949760afeprg8njbv&firstpagehit=https://www.anytimemailbox.com/s/blacktown-10-12-flushcombe-road'"
                },
                "Incoming Mail": "30 / month\nEach additional at €0.30",
                "Open & Scan": "Unlimited\n5 pages / month\nEach additional page at €0.40",
                "Forwarding": "Unlimited\nShipping fees will apply",
                "Check Deposit": "Not available",
                "Recycling": "Unlimited",
                "Shredding": "Each at €0.15",
                "Local Pickup": "€1.50 per visit\nPickup during business hours",
                "Physical Storage": "Standard Envelope: Free storage for 30 day(s), then €0.10 for every mail item per day\nLarge Envelope: Free storage for 30 day(s), then €0.10 for every mail item per day\nSmall Box: Free storage for 10 day(s), then €0.25 for every mail item per day\nMedium Box: Free storage for 10 day(s), then €0.50 for every mail item per day\nLarge Box: Free storage for 10 day(s), then €0.75 for every mail item per day\nExtra Large Box: Free storage for 10 day(s), then €1.00 for every mail item per day\nAll other mail: Free storage for 30 day(s), then €0.05 for every mail item per day",
                "Online Storage": "Unlimited",
                "Recipients": "2\nEach additional €8.00 / month"
              }
            },
            {
              "title": "Silver",
              "monthly_price": {
                "amount": 12.5,
                "currency": "USD"
              },
              "monthly_button_url": "location.href='https://signup.anytimemailbox.com/signup/new?term=30&srvPlnId=27167&siftsessionid=175205937564949760afeprg8njbv&firstpagehit=https://www.anytimemailbox.com/s/blacktown-10-12-flushcombe-road'",
              "yearly_price": {
                "amount": 137.5,
                "currency": "USD"
              },
              "yearly_button_url": "location.href='https://signup.anytimemailbox.com/signup/new?term=360&srvPlnId=27167&siftsessionid=175205937564949760afeprg8njbv&firstpagehit=https://www.anytimemailbox.com/s/blacktown-10-12-flushcombe-road'",
              "features": {
                "Incoming Mail": "60 / month",
                "Open & Scan": "10 pages / month",
                "Forwarding": "Unlimited",
                "Recipients": "4"
              },
              "service_plan_id": "27167",
              "detailed_features": {
                "pricing": {
                  "monthly_price": {
                    "amount": 12.5,
                    "currency": "USD"
                  },
                  "monthly_button_url": "location.href='https://signup.anytimemailbox.com/signup/new?term=30&srvPlnId=27167&siftsessionid=175205937564949760afeprg8njbv&firstpagehit=https://www.anytimemailbox.com/s/blacktown-10-12-flushcombe-road'",
                  "yearly_price": {
                    "amount": 137.5,
                    "currency": "USD"
                  },
                  "yearly_button_url": "location.href='https://signup.anytimemailbox.com/signup/new?term=360&srvPlnId=27167&siftsessionid=175205937564949760afeprg8njbv&firstpagehit=https://www.anytimemailbox.com/s/blacktown-10-12-flushcombe-road'"
                },
                "Incoming Mail": "60 / month\nEach additional at €0.30",
                "Open & Scan": "Unlimited\n10 pages / month\nEach additional page at €0.40",
                "Forwarding": "Unlimited\nShipping fees will apply",
                "Check Deposit": "Not available",
                "Recycling": "Unlimited",
                "Shredding": "Each at €0.15",
                "Local Pickup": "€1.50 per visit\nPickup during business hours",
                "Physical Storage": "Standard Envelope: Free storage for 30 day(s), then €0.10 for every mail item per day\nLarge Envelope: Free storage for 30 day(s), then €0.10 for every mail item per day\nPadded Mailer: Free storage for 30 day(s), then €0.10 for every mail item per day\nSmall Box: Free storage for 10 day(s), then €0.25 for every mail item per day\nMedium Box: Free storage for 10 day(s), then €0.50 for every mail item per day\nLarge Box: Free storage for 10 day(s), then €0.75 for every mail item per day\nExtra Large Box: Free storage for 10 day(s), then €1.00 for every mail item per day\nAll other mail: Free storage for 30 day(s), then €0.05 for every mail item per day",
                "Online Storage": "Unlimited",
                "Recipients": "4\nEach additional €8.00 / month"
              }
            },
            {
              "title": "Gold",
              "monthly_price": {
                "amount": 17.0,
                "currency": "USD"
              },
              "monthly_button_url": "location.href='https://signup.anytimemailbox.com/signup/new?term=30&srvPlnId=27168&siftsessionid=175205937564949760afeprg8njbv&firstpagehit=https://www.anytimemailbox.com/s/blacktown-10-12-flushcombe-road'",
              "yearly_price": {
                "amount": 187.0,
                "currency": "USD"
              },
              "yearly_button_url": "location.href='https://signup.anytimemailbox.com/signup/new?term=360&srvPlnId=27168&siftsessionid=175205937564949760afeprg8njbv&firstpagehit=https://www.anytimemailbox.com/s/blacktown-10-12-flushcombe-road'",
              "features": {
                "Incoming Mail": "125 / month",
                "Open & Scan": "20 pages / month",
                "Forwarding": "Unlimited",
                "Recipients": "4"
              },
              "service_plan_id": "27168",
              "detailed_features": {
                "pricing": {
                  "monthly_price": {
                    "amount": 17.0,
                    "currency": "USD"
                  },
                  "monthly_button_url": "location.href='https://signup.anytimemailbox.com/signup/new?term=30&srvPlnId=27168&siftsessionid=175205937564949760afeprg8njbv&firstpagehit=https://www.anytimemailbox.com/s/blacktown-10-12-flushcombe-road'",
                  "yearly_price": {
                    "amount": 187.0,
                    "currency": "USD"
                  },
                  "yearly_button_url": "location.href='https://signup.anytimemailbox.com/signup/new?term=360&srvPlnId=27168&siftsessionid=175205937564949760afeprg8njbv&firstpagehit=https://www.anytimemailbox.com/s/blacktown-10-12-flushcombe-road'"
                },
                "Incoming Mail": "125 / month\nEach additional at €0.30",
                "Open & Scan": "Unlimited\n20 pages / month\nEach additional page at €0.45",
                "Forwarding": "Unlimited\nShipping fees will apply",
                "Check Deposit": "Not available",
                "Recycling": "Unlimited",
                "Shredding": "Each at €0.15",
                "Local Pickup": "€1.50 per visit\nPickup during business hours",
                "Physical Storage": "Standard Envelope: Free storage for 30 day(s), then €0.10 for every mail item per day\nLarge Envelope: Free storage for 30 day(s), then €0.10 for every mail item per day\nPadded Mailer: Free storage for 30 day(s), then €0.10 for every mail item per day\nSmall Box: Free storage for 10 day(s), then €0.25 for every mail item per day\nMedium Box: Free storage for 10 day(s), then €0.50 for every mail item per day\nLarge Box: Free storage for 10 day(s), then €0.75 for every mail item per day\nExtra Large Box: Free storage for 10 day(s), then €1.00 for every mail item per day\nAll other mail: Free storage for 30 day(s), then €0.05 for every mail item per day",
                "Online Storage": "Unlimited",
                "Recipients": "4\nEach additional €8.00 / month"
              }
            },
            {
              "title": "Unlimited",
              "monthly_price": {
                "amount": 25.0,
                "currency": "USD"
              },
              "monthly_button_url": "location.href='https://signup.anytimemailbox.com/signup/new?term=30&srvPlnId=27169&siftsessionid=175205937564949760afeprg8njbv&firstpagehit=https://www.anytimemailbox.com/s/blacktown-10-12-flushcombe-road'",
              "yearly_price": {
                "amount": 275.0,
                "currency": "USD"
              },
              "yearly_button_url": "location.href='https://signup.anytimemailbox.com/signup/new?term=360&srvPlnId=27169&siftsessionid=175205937564949760afeprg8njbv&firstpagehit=https://www.anytimemailbox.com/s/blacktown-10-12-flushcombe-road'",
              "features": {
                "Incoming Mail": "Unlimited",
                "Open & Scan": "100 pages / month",
                "Forwarding": "Unlimited",
                "Recipients": "4"
              },
              "service_plan_id": "27169",
              "detailed_features": {
                "pricing": {
                  "monthly_price": {
                    "amount": 25.0,
                    "currency": "USD"
                  },
                  "monthly_button_url": "location.href='https://signup.anytimemailbox.com/signup/new?term=30&srvPlnId=27169&siftsessionid=175205937564949760afeprg8njbv&firstpagehit=https://www.anytimemailbox.com/s/blacktown-10-12-flushcombe-road'",
                  "yearly_price": {
                    "amount": 275.0,
                    "currency": "USD"
                  },
                  "yearly_button_url": "location.href='https://signup.anytimemailbox.com/signup/new?term=360&srvPlnId=27169&siftsessionid=175205937564949760afeprg8njbv&firstpagehit=https://www.anytimemailbox.com/s/blacktown-10-12-flushcombe-road'"
                },
                "Incoming Mail": "Unlimited",
                "Open & Scan": "Unlimited\n100 pages / month\nEach additional page at €0.45",
                "Forwarding": "Unlimited\nShipping fees will apply",
                "Check Deposit": "Not available",
                "Recycling": "Unlimited",
                "Shredding": "Unlimited",
                "Local Pickup": "€1.50 per visit\nPickup during business hours",
                "Physical Storage": "Standard Envelope: Free storage for 30 day(s), then €0.10 for every mail item per day\nLarge Envelope: Free storage for 30 day(s), then €0.10 for every mail item per day\nPadded Mailer: Free storage for 30 day(s), then €0.10 for every mail item per day\nSmall Box: Free storage for 10 day(s), then €0.25 for every mail item per day\nMedium Box: Free storage for 10 day(s), then €0.50 for every mail item per day\nLarge Box: Free storage for 10 day(s), then €0.75 for every mail item per day\nExtra Large Box: Free storage for 10 day(s), then €1.00 for every mail item per day\nAll other mail: Free storage for 30 day(s), then €0.05 for every mail item per day",
                "Online Storage": "Unlimited",
                "Recipients": "4\nEach additional €8.00 / month"
              }
            }
          ],
          "location_info": {
            "address_title": "Your Real Street Address",
            "address_text": "YOUR NAME\n{Mail Boxes Etc.}\nPP #MAILBOX Ul. Brune Bušića 42\nSredišće, Zagreb 10020 Croatia",
            "street_address": "{Mail Boxes Etc.}",
            "suite_info": "PP #MAILBOX Ul. Brune Bušića 42",
            "city_state_zip": "PP #MAILBOX Ul. Brune Bušića 42",
            "country": "Središće, Zagreb 10020 Croatia",
            "features": [
              {
                "name": "Open & Scan",
                "available": true
              },
              {
                "name": "Recycling",
                "available": true
              },
              {
                "name": "Forwarding",
                "available": true
              },
              {
                "name": "Shredding",
                "available": true
              },
              {
                "name": "Check Deposit",
                "available": false
              },
              {
                "name": "Local Pickup",
                "available": true
              }
            ],
            "shipping_carriers": [
              "Ship with FedEx",
              "Ship with UPS"
            ],
            "operator_info": {
              "name": "Mail Boxes Etc. Središće Verified",
              "verified": true
            }
          },
          "name": "Središće - Ul Brune Bušića",
          "region": "Zagreb"
        },
        {
          "title": "Zagreb - Remetinecka Cesta",
          "price": {
            "amount": 10.22,
            "currency": "USD"
          },
          "address": "Remetinečka 7A, Mail Boxes Etc., 10020, Zagreb, ZG, Croatia",
          "latitude": "45.800834",
          "longitude": "15.9116809",
          "plan_url": "https://www.anytimemailbox.com/s/zagreb-remetinecka-cesta-kajzerica",
          "is_premier": false,
          "plans": [
            {
              "title": "Bronze",
              "monthly_price": {
                "amount": 10.22,
                "currency": "USD"
              },
              "monthly_button_url": "location.href='https://signup.anytimemailbox.com/signup/new?term=30&srvPlnId=20215&siftsessionid=175205937564949760afeprg8njbv&firstpagehit=https://www.anytimemailbox.com/s/blacktown-10-12-flushcombe-road'",
              "yearly_price": {
                "amount": 103.66,
                "currency": "USD"
              },
              "yearly_button_url": "location.href='https://signup.anytimemailbox.com/signup/new?term=360&srvPlnId=20215&siftsessionid=175205937564949760afeprg8njbv&firstpagehit=https://www.anytimemailbox.com/s/blacktown-10-12-flushcombe-road'",
              "features": {
                "Incoming Mail": "30 / month",
                "Open & Scan": "5 pages / month",
                "Forwarding": "Unlimited",
                "Recipients": "2"
              },
              "service_plan_id": "20215",
              "detailed_features": {
                "pricing": {
                  "monthly_price": {
                    "amount": 10.22,
                    "currency": "USD"
                  },
                  "monthly_button_url": "location.href='https://signup.anytimemailbox.com/signup/new?term=30&srvPlnId=20215&siftsessionid=175205937564949760afeprg8njbv&firstpagehit=https://www.anytimemailbox.com/s/blacktown-10-12-flushcombe-road'",
                  "yearly_price": {
                    "amount": 103.66,
                    "currency": "USD"
                  },
                  "yearly_button_url": "location.href='https://signup.anytimemailbox.com/signup/new?term=360&srvPlnId=20215&siftsessionid=175205937564949760afeprg8njbv&firstpagehit=https://www.anytimemailbox.com/s/blacktown-10-12-flushcombe-road'"
                },
                "Incoming Mail": "30 / month\nEach additional at €0.30",
                "Open & Scan": "Unlimited\n5 pages / month\nEach additional page at €0.43",
                "Forwarding": "Unlimited\nShipping fees will apply",
                "Check Deposit": "Not available",
                "Recycling": "Unlimited",
                "Shredding": "Each at €0.14",
                "Local Pickup": "€1.73 per visit\nPickup during business hours",
                "Physical Storage": "Free storage for 30 day(s), then €0.05 for every mail item per day",
                "Online Storage": "Unlimited",
                "Recipients": "2\nEach additional €8.63 / month"
              }
            },
            {
              "title": "Silver",
              "monthly_price": {
                "amount": 14.73,
                "currency": "USD"
              },
              "monthly_button_url": "location.href='https://signup.anytimemailbox.com/signup/new?term=30&srvPlnId=20216&siftsessionid=175205937564949760afeprg8njbv&firstpagehit=https://www.anytimemailbox.com/s/blacktown-10-12-flushcombe-road'",
              "yearly_price": {
                "amount": 154.75,
                "currency": "USD"
              },
              "yearly_button_url": "location.href='https://signup.anytimemailbox.com/signup/new?term=360&srvPlnId=20216&siftsessionid=175205937564949760afeprg8njbv&firstpagehit=https://www.anytimemailbox.com/s/blacktown-10-12-flushcombe-road'",
              "features": {
                "Incoming Mail": "60 / month",
                "Open & Scan": "10 pages / month",
                "Forwarding": "No handling fees",
                "Recipients": "4"
              },
              "service_plan_id": "20216",
              "detailed_features": {
                "pricing": {
                  "monthly_price": {
                    "amount": 14.73,
                    "currency": "USD"
                  },
                  "monthly_button_url": "location.href='https://signup.anytimemailbox.com/signup/new?term=30&srvPlnId=20216&siftsessionid=175205937564949760afeprg8njbv&firstpagehit=https://www.anytimemailbox.com/s/blacktown-10-12-flushcombe-road'",
                  "yearly_price": {
                    "amount": 154.75,
                    "currency": "USD"
                  },
                  "yearly_button_url": "location.href='https://signup.anytimemailbox.com/signup/new?term=360&srvPlnId=20216&siftsessionid=175205937564949760afeprg8njbv&firstpagehit=https://www.anytimemailbox.com/s/blacktown-10-12-flushcombe-road'"
                },
                "Incoming Mail": "60 / month\nEach additional at €0.30",
                "Open & Scan": "Unlimited\n10 pages / month\nEach additional page at €0.43",
                "Forwarding": "No handling fees\nShipping fees will apply",
                "Check Deposit": "Not available",
                "Recycling": "Unlimited",
                "Shredding": "Each at €0.14",
                "Local Pickup": "€1.73 per visit\nPickup during business hours",
                "Physical Storage": "Free storage for 30 day(s), then €0.05 for every mail item per day",
                "Online Storage": "Unlimited",
                "Recipients": "4\nEach additional €8.63 / month"
              }
            },
            {
              "title": "Gold",
              "monthly_price": {
                "amount": 29.33,
                "currency": "USD"
              },
              "monthly_button_url": "location.href='https://signup.anytimemailbox.com/signup/new?term=30&srvPlnId=20212&siftsessionid=175205937564949760afeprg8njbv&firstpagehit=https://www.anytimemailbox.com/s/blacktown-10-12-flushcombe-road'",
              "yearly_price": {
                "amount": 309.38,
                "currency": "USD"
              },
              "yearly_button_url": "location.href='https://signup.anytimemailbox.com/signup/new?term=360&srvPlnId=20212&siftsessionid=175205937564949760afeprg8njbv&firstpagehit=https://www.anytimemailbox.com/s/blacktown-10-12-flushcombe-road'",
              "features": {
                "Incoming Mail": "125 / month",
                "Open & Scan": "20 pages / month",
                "Forwarding": "No handling fees",
                "Recipients": "4"
              },
              "service_plan_id": "20212",
              "detailed_features": {
                "pricing": {
                  "monthly_price": {
                    "amount": 29.33,
                    "currency": "USD"
                  },
                  "monthly_button_url": "location.href='https://signup.anytimemailbox.com/signup/new?term=30&srvPlnId=20212&siftsessionid=175205937564949760afeprg8njbv&firstpagehit=https://www.anytimemailbox.com/s/blacktown-10-12-flushcombe-road'",
                  "yearly_price": {
                    "amount": 309.38,
                    "currency": "USD"
                  },
                  "yearly_button_url": "location.href='https://signup.anytimemailbox.com/signup/new?term=360&srvPlnId=20212&siftsessionid=175205937564949760afeprg8njbv&firstpagehit=https://www.anytimemailbox.com/s/blacktown-10-12-flushcombe-road'"
                },
                "Incoming Mail": "125 / month\nEach additional at €0.30",
                "Open & Scan": "Unlimited\n20 pages / month\nEach additional page at €0.43",
                "Forwarding": "No handling fees\nShipping fees will apply",
                "Check Deposit": "Not available",
                "Recycling": "Unlimited",
                "Shredding": "Each at €0.14",
                "Local Pickup": "€1.73 per visit\nPickup during business hours",
                "Physical Storage": "Free storage for 30 day(s), then €0.05 for every mail item per day",
                "Online Storage": "Unlimited",
                "Recipients": "4\nEach additional €8.63 / month"
              }
            },
            {
              "title": "Unlimited",
              "monthly_price": {
                "amount": 65.83,
                "currency": "USD"
              },
              "monthly_button_url": "location.href='https://signup.anytimemailbox.com/signup/new?term=30&srvPlnId=20213&siftsessionid=175205937564949760afeprg8njbv&firstpagehit=https://www.anytimemailbox.com/s/blacktown-10-12-flushcombe-road'",
              "yearly_price": {
                "amount": 617.29,
                "currency": "USD"
              },
              "yearly_button_url": "location.href='https://signup.anytimemailbox.com/signup/new?term=360&srvPlnId=20213&siftsessionid=175205937564949760afeprg8njbv&firstpagehit=https://www.anytimemailbox.com/s/blacktown-10-12-flushcombe-road'",
              "features": {
                "Incoming Mail": "Unlimited",
                "Open & Scan": "100 pages / month",
                "Forwarding": "No handling fees",
                "Recipients": "4"
              },
              "service_plan_id": "20213",
              "detailed_features": {
                "pricing": {
                  "monthly_price": {
                    "amount": 65.83,
                    "currency": "USD"
                  },
                  "monthly_button_url": "location.href='https://signup.anytimemailbox.com/signup/new?term=30&srvPlnId=20213&siftsessionid=175205937564949760afeprg8njbv&firstpagehit=https://www.anytimemailbox.com/s/blacktown-10-12-flushcombe-road'",
                  "yearly_price": {
                    "amount": 617.29,
                    "currency": "USD"
                  },
                  "yearly_button_url": "location.href='https://signup.anytimemailbox.com/signup/new?term=360&srvPlnId=20213&siftsessionid=175205937564949760afeprg8njbv&firstpagehit=https://www.anytimemailbox.com/s/blacktown-10-12-flushcombe-road'"
                },
                "Incoming Mail": "Unlimited",
                "Open & Scan": "Unlimited\n100 pages / month\nEach additional page at €0.43",
                "Forwarding": "No handling fees\nShipping fees will apply",
                "Check Deposit": "Not available",
                "Recycling": "Unlimited",
                "Shredding": "Unlimited",
                "Local Pickup": "€1.73 per visit\nPickup during business hours",
                "Physical Storage": "Free storage for 30 day(s), then €0.05 for every mail item per day",
                "Online Storage": "Unlimited",
                "Recipients": "4\nEach additional €8.63 / month"
              }
            }
          ],
          "location_info": {
            "address_title": "Your Real Street Address",
            "address_text": "YOUR NAME\nUnit #MAILBOX\nRemetinečka 7A, Mail Boxes Etc.\n10020\nZagreb, ZG\nCroatia",
            "street_address": "Unit #MAILBOX",
            "suite_info": "Unit #MAILBOX",
            "city_state_zip": "Zagreb, ZG",
            "country": "Croatia",
            "features": [
              {
                "name": "Open & Scan",
                "available": true
              },
              {
                "name": "Recycling",
                "available": true
              },
              {
                "name": "Forwarding",
                "available": true
              },
              {
                "name": "Shredding",
                "available": true
              },
              {
                "name": "Check Deposit",
                "available": false
              },
              {
                "name": "Local Pickup",
                "available": true
              }
            ],
            "shipping_carriers": [
              "Ship with FedEx",
              "Ship with DHL"
            ],
            "operator_info": {
              "name": "Mail Boxes Etc. Zagreb Verified",
              "verified": true
            }
          },
          "name": "Zagreb - Remetinecka Cesta",
          "region": "Zagreb"
        },
        {
          "title": "Zagreb - Vlaska Ul",
          "price": {
            "amount": 10.0,
            "currency": "USD"
          },
          "address": "Vlaška ulica 45, 10000 Zagreb, Croatia, Croatia",
          "latitude": "45.8139105",
          "longitude": "15.9828261",
          "plan_url": "https://www.anytimemailbox.com/s/zagreb-vlaska-ulica-45",
          "is_premier": false,
          "plans": [
            {
              "title": "Bronze",
              "monthly_price": {
                "amount": 10.0,
                "currency": "USD"
              },
              "monthly_button_url": "location.href='https://signup.anytimemailbox.com/signup/new?term=30&srvPlnId=24212&siftsessionid=175205937564949760afeprg8njbv&firstpagehit=https://www.anytimemailbox.com/s/blacktown-10-12-flushcombe-road'",
              "yearly_price": {
                "amount": 103.66,
                "currency": "USD"
              },
              "yearly_button_url": "location.href='https://signup.anytimemailbox.com/signup/new?term=360&srvPlnId=24212&siftsessionid=175205937564949760afeprg8njbv&firstpagehit=https://www.anytimemailbox.com/s/blacktown-10-12-flushcombe-road'",
              "features": {
                "Incoming Mail": "30 / month",
                "Open & Scan": "5 pages / month",
                "Forwarding": "Unlimited",
                "Recipients": "2"
              },
              "service_plan_id": "24212",
              "detailed_features": {
                "pricing": {
                  "monthly_price": {
                    "amount": 10.0,
                    "currency": "USD"
                  },
                  "monthly_button_url": "location.href='https://signup.anytimemailbox.com/signup/new?term=30&srvPlnId=24212&siftsessionid=175205937564949760afeprg8njbv&firstpagehit=https://www.anytimemailbox.com/s/blacktown-10-12-flushcombe-road'",
                  "yearly_price": {
                    "amount": 103.66,
                    "currency": "USD"
                  },
                  "yearly_button_url": "location.href='https://signup.anytimemailbox.com/signup/new?term=360&srvPlnId=24212&siftsessionid=175205937564949760afeprg8njbv&firstpagehit=https://www.anytimemailbox.com/s/blacktown-10-12-flushcombe-road'"
                },
                "Incoming Mail": "30 / month\nEach additional at €0.30",
                "Open & Scan": "Unlimited\n5 pages / month\nEach additional page at €0.43",
                "Forwarding": "Unlimited\nShipping fees will apply",
                "Check Deposit": "Not available",
                "Recycling": "Unlimited",
                "Shredding": "Each at €0.14",
                "Local Pickup": "€1.73 per visit\nPickup during business hours",
                "Physical Storage": "Standard Envelope: Free storage for 30 day(s), then €0.10 for every mail item per day\nLarge Envelope: Free storage for 30 day(s), then €0.10 for every mail item per day\nPadded Mailer: Free storage for 30 day(s), then €0.10 for every mail item per day\nSmall Box: Free storage for 10 day(s), then €0.25 for every mail item per day\nMedium Box: Free storage for 10 day(s), then €0.50 for every mail item per day\nLarge Box: Free storage for 10 day(s), then €0.75 for every mail item per day\nExtra Large Box: Free storage for 10 day(s), then €1.00 for every mail item per day\nAll other mail: Free storage for 30 day(s), then €0.05 for every mail item per day",
                "Online Storage": "Unlimited",
                "Recipients": "2\nEach additional €8.63 / month"
              }
            },
            {
              "title": "Silver",
              "monthly_price": {
                "amount": 14.73,
                "currency": "USD"
              },
              "monthly_button_url": "location.href='https://signup.anytimemailbox.com/signup/new?term=30&srvPlnId=24213&siftsessionid=175205937564949760afeprg8njbv&firstpagehit=https://www.anytimemailbox.com/s/blacktown-10-12-flushcombe-road'",
              "yearly_price": {
                "amount": 154.75,
                "currency": "USD"
              },
              "yearly_button_url": "location.href='https://signup.anytimemailbox.com/signup/new?term=360&srvPlnId=24213&siftsessionid=175205937564949760afeprg8njbv&firstpagehit=https://www.anytimemailbox.com/s/blacktown-10-12-flushcombe-road'",
              "features": {
                "Incoming Mail": "60 / month",
                "Open & Scan": "10 pages / month",
                "Forwarding": "Unlimited",
                "Recipients": "4"
              },
              "service_plan_id": "24213",
              "detailed_features": {
                "pricing": {
                  "monthly_price": {
                    "amount": 14.73,
                    "currency": "USD"
                  },
                  "monthly_button_url": "location.href='https://signup.anytimemailbox.com/signup/new?term=30&srvPlnId=24213&siftsessionid=175205937564949760afeprg8njbv&firstpagehit=https://www.anytimemailbox.com/s/blacktown-10-12-flushcombe-road'",
                  "yearly_price": {
                    "amount": 154.75,
                    "currency": "USD"
                  },
                  "yearly_button_url": "location.href='https://signup.anytimemailbox.com/signup/new?term=360&srvPlnId=24213&siftsessionid=175205937564949760afeprg8njbv&firstpagehit=https://www.anytimemailbox.com/s/blacktown-10-12-flushcombe-road'"
                },
                "Incoming Mail": "60 / month\nEach additional at €0.30",
                "Open & Scan": "Unlimited\n10 pages / month\nEach additional page at €0.43",
                "Forwarding": "Unlimited\nShipping fees will apply",
                "Check Deposit": "Not available",
                "Recycling": "Unlimited",
                "Shredding": "Each at €0.14",
                "Local Pickup": "€1.73 per visit\nPickup during business hours",
                "Physical Storage": "Standard Envelope: Free storage for 30 day(s), then €0.10 for every mail item per day\nLarge Envelope: Free storage for 30 day(s), then €0.10 for every mail item per day\nPadded Mailer: Free storage for 30 day(s), then €0.10 for every mail item per day\nSmall Box: Free storage for 10 day(s), then €0.25 for every mail item per day\nMedium Box: Free storage for 10 day(s), then €0.50 for every mail item per day\nLarge Box: Free storage for 10 day(s), then €0.75 for every mail item per day\nExtra Large Box: Free storage for 10 day(s), then €1.00 for every mail item per day\nAll other mail: Free storage for 30 day(s), then €0.05 for every mail item per day",
                "Online Storage": "Unlimited",
                "Recipients": "4\nEach additional €8.63 / month"
              }
            },
            {
              "title": "Gold",
              "monthly_price": {
                "amount": 29.33,
                "currency": "USD"
              },
              "monthly_button_url": "location.href='https://signup.anytimemailbox.com/signup/new?term=30&srvPlnId=24214&siftsessionid=175205937564949760afeprg8njbv&firstpagehit=https://www.anytimemailbox.com/s/blacktown-10-12-flushcombe-road'",
              "yearly_price": {
                "amount": 309.38,
                "currency": "USD"
              },
              "yearly_button_url": "location.href='https://signup.anytimemailbox.com/signup/new?term=360&srvPlnId=24214&siftsessionid=175205937564949760afeprg8njbv&firstpagehit=https://www.anytimemailbox.com/s/blacktown-10-12-flushcombe-road'",
              "features": {
                "Incoming Mail": "125 / month",
                "Open & Scan": "20 pages / month",
                "Forwarding": "Unlimited",
                "Recipients": "4"
              },
              "service_plan_id": "24214",
              "detailed_features": {
                "pricing": {
                  "monthly_price": {
                    "amount": 29.33,
                    "currency": "USD"
                  },
                  "monthly_button_url": "location.href='https://signup.anytimemailbox.com/signup/new?term=30&srvPlnId=24214&siftsessionid=175205937564949760afeprg8njbv&firstpagehit=https://www.anytimemailbox.com/s/blacktown-10-12-flushcombe-road'",
                  "yearly_price": {
                    "amount": 309.38,
                    "currency": "USD"
                  },
                  "yearly_button_url": "location.href='https://signup.anytimemailbox.com/signup/new?term=360&srvPlnId=24214&siftsessionid=175205937564949760afeprg8njbv&firstpagehit=https://www.anytimemailbox.com/s/blacktown-10-12-flushcombe-road'"
                },
                "Incoming Mail": "125 / month\nEach additional at €0.30",
                "Open & Scan": "Unlimited\n20 pages / month\nEach additional page at €0.43",
                "Forwarding": "Unlimited\nShipping fees will apply",
                "Check Deposit": "Not available",
                "Recycling": "Unlimited",
                "Shredding": "Each at €0.14",
                "Local Pickup": "€1.73 per visit\nPickup during business hours",
                "Physical Storage": "Standard Envelope: Free storage for 30 day(s), then €0.10 for every mail item per day\nLarge Envelope: Free storage for 30 day(s), then €0.10 for every mail item per day\nPadded Mailer: Free storage for 30 day(s), then €0.10 for every mail item per day\nSmall Box: Free storage for 10 day(s), then €0.25 for every mail item per day\nMedium Box: Free storage for 10 day(s), then €0.50 for every mail item per day\nLarge Box: Free storage for 10 day(s), then €0.75 for every mail item per day\nExtra Large Box: Free storage for 10 day(s), then €1.00 for every mail item per day\nAll other mail: Free storage for 30 day(s), then €0.05 for every mail item per day",
                "Online Storage": "Unlimited",
                "Recipients": "4\nEach additional €8.63 / month"
              }
            },
            {
              "title": "Unlimited",
              "monthly_price": {
                "amount": 65.83,
                "currency": "USD"
              },
              "monthly_button_url": "location.href='https://signup.anytimemailbox.com/signup/new?term=30&srvPlnId=24215&siftsessionid=175205937564949760afeprg8njbv&firstpagehit=https://www.anytimemailbox.com/s/blacktown-10-12-flushcombe-road'",
              "yearly_price": {
                "amount": 617.29,
                "currency": "USD"
              },
              "yearly_button_url": "location.href='https://signup.anytimemailbox.com/signup/new?term=360&srvPlnId=24215&siftsessionid=175205937564949760afeprg8njbv&firstpagehit=https://www.anytimemailbox.com/s/blacktown-10-12-flushcombe-road'",
              "features": {
                "Incoming Mail": "Unlimited",
                "Open & Scan": "100 pages / month",
                "Forwarding": "Unlimited",
                "Recipients": "4"
              },
              "service_plan_id": "24215",
              "detailed_features": {
                "pricing": {
                  "monthly_price": {
                    "amount": 65.83,
                    "currency": "USD"
                  },
                  "monthly_button_url": "location.href='https://signup.anytimemailbox.com/signup/new?term=30&srvPlnId=24215&siftsessionid=175205937564949760afeprg8njbv&firstpagehit=https://www.anytimemailbox.com/s/blacktown-10-12-flushcombe-road'",
                  "yearly_price": {
                    "amount": 617.29,
                    "currency": "USD"
                  },
                  "yearly_button_url": "location.href='https://signup.anytimemailbox.com/signup/new?term=360&srvPlnId=24215&siftsessionid=175205937564949760afeprg8njbv&firstpagehit=https://www.anytimemailbox.com/s/blacktown-10-12-flushcombe-road'"
                },
                "Incoming Mail": "Unlimited",
                "Open & Scan": "Unlimited\n100 pages / month\nEach additional page at €0.43",
                "Forwarding": "Unlimited\nShipping fees will apply",
                "Check Deposit": "Not available",
                "Recycling": "Unlimited",
                "Shredding": "Unlimited",
                "Local Pickup": "€1.73 per visit\nPickup during business hours",
                "Physical Storage": "Standard Envelope: Free storage for 30 day(s), then €0.10 for every mail item per day\nLarge Envelope: Free storage for 30 day(s), then €0.10 for every mail item per day\nPadded Mailer: Free storage for 30 day(s), then €0.10 for every mail item per day\nSmall Box: Free storage for 10 day(s), then €0.25 for every mail item per day\nMedium Box: Free storage for 10 day(s), then €0.50 for every mail item per day\nLarge Box: Free storage for 10 day(s), then €0.75 for every mail item per day\nExtra Large Box: Free storage for 10 day(s), then €1.00 for every mail item per day\nAll other mail: Free storage for 30 day(s), then €0.05 for every mail item per day",
                "Online Storage": "Unlimited",
                "Recipients": "4\nEach additional €8.63 / month"
              }
            }
          ],
          "location_info": {
            "address_title": "Your Real Street Address",
            "address_text": "YOUR NAME\nUnit #MAILBOX\nVlaška ulica 45\n10000 Zagreb, Croatia\nCroatia",
            "street_address": "Unit #MAILBOX",
            "suite_info": "Unit #MAILBOX",
            "city_state_zip": "10000 Zagreb, Croatia",
            "country": "Croatia",
            "features": [
              {
                "name": "Open & Scan",
                "available": true
              },
              {
                "name": "Recycling",
                "available": true
              },
              {
                "name": "Forwarding",
                "available": true
              },
              {
                "name": "Shredding",
                "available": true
              },
              {
                "name": "Check Deposit",
                "available": false
              },
              {
                "name": "Local Pickup",
                "available": true
              }
            ],
            "shipping_carriers": [
              "Ship with FedEx"
            ],
            "operator_info": {
              "name": "Mail Boxes Etc. Zagreb-Centar Verified",
              "verified": true
            }
          },
          "name": "Zagreb - Vlaska Ul",
          "region": "Zagreb"
        }
      ],
      "location_count": 3
    },
    {
      "region": "Central Croatia",
      "locations": [
        {
          "title": "Križevci",
          "price": {
            "amount": 9.99,
            "currency": "USD"
          },
          "address": "Ul. bana Josipa Jelačića 1, Križevci, Croatia",
          "latitude": "46.0247184",
          "longitude": "16.5465992",
          "plan_url": "https://www.anytimemailbox.com/s/krizevci-ul-bana-josipa-jelacica-1",
          "is_premier": false,
          "plans": [
            {
              "title": "Bronze",
              "monthly_price": {
                "amount": 9.99,
                "currency": "USD"
              },
              "monthly_button_url": "location.href='https://signup.anytimemailbox.com/signup/new?term=30&srvPlnId=23128&siftsessionid=175205937564949760afeprg8njbv&firstpagehit=https://www.anytimemailbox.com/s/blacktown-10-12-flushcombe-road'",
              "yearly_price": {
                "amount": 109.99,
                "currency": "USD"
              },
              "yearly_button_url": "location.href='https://signup.anytimemailbox.com/signup/new?term=360&srvPlnId=23128&siftsessionid=175205937564949760afeprg8njbv&firstpagehit=https://www.anytimemailbox.com/s/blacktown-10-12-flushcombe-road'",
              "features": {
                "Incoming Mail": "30 / month",
                "Open & Scan": "5 pages / month",
                "Forwarding": "Each shipping bundle at €5.00",
                "Recipients": "1"
              },
              "service_plan_id": "23128",
              "detailed_features": {
                "pricing": {
                  "monthly_price": {
                    "amount": 9.99,
                    "currency": "USD"
                  },
                  "monthly_button_url": "location.href='https://signup.anytimemailbox.com/signup/new?term=30&srvPlnId=23128&siftsessionid=175205937564949760afeprg8njbv&firstpagehit=https://www.anytimemailbox.com/s/blacktown-10-12-flushcombe-road'",
                  "yearly_price": {
                    "amount": 109.99,
                    "currency": "USD"
                  },
                  "yearly_button_url": "location.href='https://signup.anytimemailbox.com/signup/new?term=360&srvPlnId=23128&siftsessionid=175205937564949760afeprg8njbv&firstpagehit=https://www.anytimemailbox.com/s/blacktown-10-12-flushcombe-road'"
                },
                "Incoming Mail": "30 / month\nEach additional at €0.35",
                "Open & Scan": "Unlimited\n5 pages / month\nEach additional page at €0.50",
                "Forwarding": "Each shipping bundle at €5.00\nShipping fees will apply",
                "Check Deposit": "Not available",
                "Recycling": "Unlimited",
                "Shredding": "Each at €0.15",
                "Local Pickup": "€2.00 per visit\nPickup during business hours",
                "Physical Storage": "Standard Envelope: Free storage for 30 day(s), then €0.10 for every mail item per day\nLarge Envelope: Free storage for 30 day(s), then €0.10 for every mail item per day\nPadded Mailer: Free storage for 30 day(s), then €0.10 for every mail item per day\nSmall Box: Free storage for 10 day(s), then €0.25 for every mail item per day\nMedium Box: Free storage for 10 day(s), then €0.50 for every mail item per day\nLarge Box: Free storage for 10 day(s), then €0.75 for every mail item per day\nExtra Large Box: Free storage for 10 day(s), then €1.00 for every mail item per day\nAll other mail: Free storage for 30 day(s), then €0.05 for every mail item per day",
                "Online Storage": "Unlimited",
                "Recipients": "1\nEach additional €10.00 / month"
              }
            },
            {
              "title": "Silver",
              "monthly_price": {
                "amount": 14.99,
                "currency": "USD"
              },
              "monthly_button_url": "location.href='https://signup.anytimemailbox.com/signup/new?term=30&srvPlnId=23129&siftsessionid=175205937564949760afeprg8njbv&firstpagehit=https://www.anytimemailbox.com/s/blacktown-10-12-flushcombe-road'",
              "yearly_price": {
                "amount": 164.99,
                "currency": "USD"
              },
              "yearly_button_url": "location.href='https://signup.anytimemailbox.com/signup/new?term=360&srvPlnId=23129&siftsessionid=175205937564949760afeprg8njbv&firstpagehit=https://www.anytimemailbox.com/s/blacktown-10-12-flushcombe-road'",
              "features": {
                "Incoming Mail": "60 / month",
                "Open & Scan": "10 pages / month",
                "Forwarding": "Each shipping bundle at €5.00",
                "Recipients": "2"
              },
              "service_plan_id": "23129",
              "detailed_features": {
                "pricing": {
                  "monthly_price": {
                    "amount": 14.99,
                    "currency": "USD"
                  },
                  "monthly_button_url": "location.href='https://signup.anytimemailbox.com/signup/new?term=30&srvPlnId=23129&siftsessionid=175205937564949760afeprg8njbv&firstpagehit=https://www.anytimemailbox.com/s/blacktown-10-12-flushcombe-road'",
                  "yearly_price": {
                    "amount": 164.99,
                    "currency": "USD"
                  },
                  "yearly_button_url": "location.href='https://signup.anytimemailbox.com/signup/new?term=360&srvPlnId=23129&siftsessionid=175205937564949760afeprg8njbv&firstpagehit=https://www.anytimemailbox.com/s/blacktown-10-12-flushcombe-road'"
                },
                "Incoming Mail": "60 / month\nEach additional at €0.35",
                "Open & Scan": "Unlimited\n10 pages / month\nEach additional page at €0.50",
                "Forwarding": "Each shipping bundle at €5.00\nShipping fees will apply",
                "Check Deposit": "Not available",
                "Recycling": "Unlimited",
                "Shredding": "Each at €0.15",
                "Local Pickup": "€2.00 per visit\nPickup during business hours",
                "Physical Storage": "Standard Envelope: Free storage for 30 day(s), then €0.10 for every mail item per day\nLarge Envelope: Free storage for 30 day(s), then €0.10 for every mail item per day\nPadded Mailer: Free storage for 30 day(s), then €0.10 for every mail item per day\nSmall Box: Free storage for 10 day(s), then €0.25 for every mail item per day\nMedium Box: Free storage for 10 day(s), then €0.50 for every mail item per day\nLarge Box: Free storage for 10 day(s), then €0.75 for every mail item per day\nExtra Large Box: Free storage for 10 day(s), then €1.00 for every mail item per day\nAll other mail: Free storage for 30 day(s), then €0.05 for every mail item per day",
                "Online Storage": "Unlimited",
                "Recipients": "2\nEach additional €10.00 / month"
              }
            },
            {
              "title": "Gold",
              "monthly_price": {
                "amount": 29.99,
                "currency": "USD"
              },
              "monthly_button_url": "location.href='https://signup.anytimemailbox.com/signup/new?term=30&srvPlnId=23130&siftsessionid=175205937564949760afeprg8njbv&firstpagehit=https://www.anytimemailbox.com/s/blacktown-10-12-flushcombe-road'",
              "yearly_price": {
                "amount": 329.99,
                "currency": "USD"
              },
              "yearly_button_url": "location.href='https://signup.anytimemailbox.com/signup/new?term=360&srvPlnId=23130&siftsessionid=175205937564949760afeprg8njbv&firstpagehit=https://www.anytimemailbox.com/s/blacktown-10-12-flushcombe-road'",
              "features": {
                "Incoming Mail": "125 / month",
                "Open & Scan": "20 pages / month",
                "Forwarding": "Each shipping bundle at €5.00",
                "Recipients": "3"
              },
              "service_plan_id": "23130",
              "detailed_features": {
                "pricing": {
                  "monthly_price": {
                    "amount": 29.99,
                    "currency": "USD"
                  },
                  "monthly_button_url": "location.href='https://signup.anytimemailbox.com/signup/new?term=30&srvPlnId=23130&siftsessionid=175205937564949760afeprg8njbv&firstpagehit=https://www.anytimemailbox.com/s/blacktown-10-12-flushcombe-road'",
                  "yearly_price": {
                    "amount": 329.99,
                    "currency": "USD"
                  },
                  "yearly_button_url": "location.href='https://signup.anytimemailbox.com/signup/new?term=360&srvPlnId=23130&siftsessionid=175205937564949760afeprg8njbv&firstpagehit=https://www.anytimemailbox.com/s/blacktown-10-12-flushcombe-road'"
                },
                "Incoming Mail": "125 / month\nEach additional at €0.35",
                "Open & Scan": "Unlimited\n20 pages / month\nEach additional page at €0.50",
                "Forwarding": "Each shipping bundle at €5.00\nShipping fees will apply",
                "Check Deposit": "Not available",
                "Recycling": "Unlimited",
                "Shredding": "Each at €0.15",
                "Local Pickup": "€2.00 per visit\nPickup during business hours",
                "Physical Storage": "Standard Envelope: Free storage for 30 day(s), then €0.10 for every mail item per day\nLarge Envelope: Free storage for 30 day(s), then €0.10 for every mail item per day\nPadded Mailer: Free storage for 30 day(s), then €0.10 for every mail item per day\nSmall Box: Free storage for 10 day(s), then €0.25 for every mail item per day\nMedium Box: Free storage for 10 day(s), then €0.50 for every mail item per day\nLarge Box: Free storage for 10 day(s), then €0.75 for every mail item per day\nExtra Large Box: Free storage for 10 day(s), then €1.00 for every mail item per day\nAll other mail: Free storage for 30 day(s), then €0.05 for every mail item per day",
                "Online Storage": "Unlimited",
                "Recipients": "3\nEach additional €10.00 / month"
              }
            },
            {
              "title": "Unlimited",
              "monthly_price": {
                "amount": 69.99,
                "currency": "USD"
              },
              "monthly_button_url": "location.href='https://signup.anytimemailbox.com/signup/new?term=30&srvPlnId=23131&siftsessionid=175205937564949760afeprg8njbv&firstpagehit=https://www.anytimemailbox.com/s/blacktown-10-12-flushcombe-road'",
              "yearly_price": {
                "amount": 659.99,
                "currency": "USD"
              },
              "yearly_button_url": "location.href='https://signup.anytimemailbox.com/signup/new?term=360&srvPlnId=23131&siftsessionid=175205937564949760afeprg8njbv&firstpagehit=https://www.anytimemailbox.com/s/blacktown-10-12-flushcombe-road'",
              "features": {
                "Incoming Mail": "Unlimited",
                "Open & Scan": "100 pages / month",
                "Forwarding": "Each shipping bundle at €5.00",
                "Recipients": "4"
              },
              "service_plan_id": "23131",
              "detailed_features": {
                "pricing": {
                  "monthly_price": {
                    "amount": 69.99,
                    "currency": "USD"
                  },
                  "monthly_button_url": "location.href='https://signup.anytimemailbox.com/signup/new?term=30&srvPlnId=23131&siftsessionid=175205937564949760afeprg8njbv&firstpagehit=https://www.anytimemailbox.com/s/blacktown-10-12-flushcombe-road'",
                  "yearly_price": {
                    "amount": 659.99,
                    "currency": "USD"
                  },
                  "yearly_button_url": "location.href='https://signup.anytimemailbox.com/signup/new?term=360&srvPlnId=23131&siftsessionid=175205937564949760afeprg8njbv&firstpagehit=https://www.anytimemailbox.com/s/blacktown-10-12-flushcombe-road'"
                },
                "Incoming Mail": "Unlimited",
                "Open & Scan": "Unlimited\n100 pages / month\nEach additional page at €0.50",
                "Forwarding": "Each shipping bundle at €5.00\nShipping fees will apply",
                "Check Deposit": "Not available",
                "Recycling": "Unlimited",
                "Shredding": "Unlimited",
                "Local Pickup": "€2.00 per visit\nPickup during business hours",
                "Physical Storage": "Standard Envelope: Free storage for 30 day(s), then €0.10 for every mail item per day\nLarge Envelope: Free storage for 30 day(s), then €0.10 for every mail item per day\nPadded Mailer: Free storage for 30 day(s), then €0.10 for every mail item per day\nSmall Box: Free storage for 10 day(s), then €0.25 for every mail item per day\nMedium Box: Free storage for 10 day(s), then €0.50 for every mail item per day\nLarge Box: Free storage for 10 day(s), then €0.75 for every mail item per day\nExtra Large Box: Free storage for 10 day(s), then €1.00 for every mail item per day\nAll other mail: Free storage for 30 day(s), then €0.05 for every mail item per day",
                "Online Storage": "Unlimited",
                "Recipients": "4\nEach additional €10.00 / month"
              }
            }
          ],
          "location_info": {
            "address_title": "Your Real Street Address",
            "address_text": "YOUR NAME\nUl. bana Josipa Jelačića 1\nUnit #MAILBOX, 48260\nKriževci, Croatia",
            "street_address": "Ul. bana Josipa Jelačića 1",
            "suite_info": "Unit #MAILBOX, 48260",
            "city_state_zip": "Unit #MAILBOX, 48260",
            "country": "Križevci, Croatia",
            "features": [
              {
                "name": "Open & Scan",
                "available": true
              },
              {
                "name": "Recycling",
                "available": true
              },
              {
                "name": "Forwarding",
                "available": true
              },
              {
                "name": "Shredding",
                "available": true
              },
              {
                "name": "Check Deposit",
                "available": false
              },
              {
                "name": "Local Pickup",
                "available": true
              }
            ],
            "shipping_carriers": [
              "Ship with FedEx",
              "Ship with UPS",
              "Ship with DHL"
            ],
            "operator_info": {
              "name": "Mail Boxes Etc. Križevci Verified",
              "verified": true
            }
          },
          "name": "Central Croatia",
          "region": "Central Croatia"
        }
      ],
      "location_count": 1
    }
  ],
  "total_locations": 4,
  "scraped_at": "2025-07-09T07:49:40.304087"
}